pysnc/__init__.py
pysnc/__version__.py
pysnc/asyncio/__init__.py
pysnc/asyncio/attachment.py
pysnc/asyncio/auth.py
pysnc/asyncio/client.py
pysnc/asyncio/record.py
pysnc/attachment.py
pysnc/auth.py
pysnc/client.py
pysnc/exceptions.py
pysnc/query.py
pysnc/record.py
pysnc/utils.py
pysnc-1.2.0.dist-info/LICENSE
pysnc-1.2.0.dist-info/METADATA
pysnc-1.2.0.dist-info/WHEEL
pysnc-1.2.0.dist-info/RECORD
